api_schema/__init__.py
api_schema/base.py
api_schema/embedding.py
api_schema/generation.py
jinaai_api_schema-0.0.1.dist-info/METADATA
jinaai_api_schema-0.0.1.dist-info/WHEEL
jinaai_api_schema-0.0.1.dist-info/top_level.txt
jinaai_api_schema-0.0.1.dist-info/RECORD
