Metadata-Version: 2.1
Name: jinaai-api-schema
Version: 0.0.1
Summary: The schemas for the Jina Serving API
Download-URL: https://github.com/jina-ai/jinaai-api-schema/tags
Author: Jina AI
Author-email: hello@jina.ai
License: Proprietary
Project-URL: Source, https://github.com/jina-ai/jinaai-api-schema.fit/
Project-URL: Tracker, https://github.com/jina-ai/jinaai-api-schema/issues
Classifier: Development Status :: 5 - Production/Stable
Classifier: Intended Audience :: Developers
Classifier: Intended Audience :: Education
Classifier: Intended Audience :: Science/Research
Classifier: Programming Language :: Python :: 3.8
Classifier: Programming Language :: Python :: 3.9
Classifier: Programming Language :: Python :: 3.10
Classifier: Environment :: Console
Classifier: Operating System :: OS Independent
Classifier: Topic :: Scientific/Engineering :: Artificial Intelligence
Requires-Python: >=3.8.0
Requires-Dist: pydantic ==1.10.10
Requires-Dist: fastapi ==0.99.0
Requires-Dist: docarray >=0.37.0
